odoo10_addon_l10n_nl_intrastat-10.0.1.0.2-py2.7-nspkg.pth
odoo/addons/l10n_nl_intrastat/README.rst
odoo/addons/l10n_nl_intrastat/__init__.py
odoo/addons/l10n_nl_intrastat/__manifest__.py
odoo/addons/l10n_nl_intrastat/data/report_layouts.xml
odoo/addons/l10n_nl_intrastat/i18n/l10n_nl_intrastat.pot
odoo/addons/l10n_nl_intrastat/i18n/nl.po
odoo/addons/l10n_nl_intrastat/i18n/nl_NL.po
odoo/addons/l10n_nl_intrastat/models/__init__.py
odoo/addons/l10n_nl_intrastat/models/l10n_nl_intrastat.py
odoo/addons/l10n_nl_intrastat/report/l10n_nl_intrastat.xml
odoo/addons/l10n_nl_intrastat/report/reports.xml
odoo/addons/l10n_nl_intrastat/security/ir.model.access.csv
odoo/addons/l10n_nl_intrastat/security/l10n_nl_report_intrastat_security.xml
odoo/addons/l10n_nl_intrastat/static/src/css/report.css
odoo/addons/l10n_nl_intrastat/tests/__init__.py
odoo/addons/l10n_nl_intrastat/tests/test_all.py
odoo/addons/l10n_nl_intrastat/views/l10n_nl_intrastat.xml
odoo10_addon_l10n_nl_intrastat-10.0.1.0.2.dist-info/METADATA
odoo10_addon_l10n_nl_intrastat-10.0.1.0.2.dist-info/RECORD
odoo10_addon_l10n_nl_intrastat-10.0.1.0.2.dist-info/WHEEL
odoo10_addon_l10n_nl_intrastat-10.0.1.0.2.dist-info/namespace_packages.txt
odoo10_addon_l10n_nl_intrastat-10.0.1.0.2.dist-info/top_level.txt
