Metadata-Version: 2.1
Name: odoo10-addon-l10n-nl-intrastat
Version: 10.0.1.0.2
Summary: Intracom Tax Report for the Netherlands
Home-page: https://github.com/OCA/intrastat
Author: Therp BV, Odoo Community Association (OCA)
Author-email: support@odoo-community.org
License: AGPL-3
Platform: UNKNOWN
Classifier: Programming Language :: Python
Classifier: Framework :: Odoo
Classifier: License :: OSI Approved :: GNU Affero General Public License v3
Requires-Python: ~=2.7
Requires-Dist: odoo10-addon-date-range
Requires-Dist: odoo10-addon-intrastat-base
Requires-Dist: odoo (<10.1dev,>=10.0)
